.gitignore
.readthedocs.yaml
CMakeLists.txt
INSTALL.md
LICENSE.txt
README.md
bitbucket-pipelines.yml
print_version.py
pyproject.toml
requirements.txt
setup.py
bench/ED/bench_ED.py
bench/ED/bench_ED2.py
bench/ED/bench_ED2_laptop.txt
bench/ED/bench_GS.py
bench/ED/bench_GS2.py
bench/ED/bench_GS_loop.py
bench/ED/model_1D.py
bench/ED/model_2D.py
bench/ED/plot_bench_ED.py
bench/integrals/plot_concurrent.py
bench/integrals/plot_integrals.py
bench/integrals/small/integrals_small.py
bench/integrals/small/integrals_small_concurrent.txt
bench/integrals/small/integrals_small_results.txt
bench/integrals/small/model_small.py
bench/vca/bench_vca.py
bench/vca/bench_vca2.py
docs/Makefile
docs/makedoc
docs/source/2x2.png
docs/source/T6.png
docs/source/cdmft.rst
docs/source/conf.py
docs/source/defining_cluster_models.rst
docs/source/defining_models.rst
docs/source/h4-6b.png
docs/source/h8.asy
docs/source/h8.png
docs/source/hartree.rst
docs/source/hexa6.png
docs/source/index.rst
docs/source/intro.rst
docs/source/models.rst
docs/source/options.rst
docs/source/options_intro.txt
docs/source/other_functions.rst
docs/source/parallel.rst
docs/source/parallel_performance_concurrent.png
docs/source/parallel_performance_ed.png
docs/source/parallel_performance_integrals.png
docs/source/parameters.rst
docs/source/t15.png
docs/source/vca.rst
examples/1D_2_4b/QCM_params.def
examples/1D_2_4b/averages.tsv
examples/1D_2_4b/cdmft.tsv
examples/1D_2_4b/cdmft_distance.tsv
examples/1D_2_4b/cdmft_grid.tsv
examples/1D_2_4b/cdmft_iter.tsv
examples/1D_2_4b/debug.py
examples/1D_2_4b/debug_complex.py
examples/1D_2_4b/debug_dvmc.py
examples/1D_2_4b/debug_variable_parameter.py
examples/1D_2_4b/dos.tsv
examples/1D_2_4b/h1.pdf
examples/1D_2_4b/h2.pdf
examples/1D_2_4b/hop.npy
examples/1D_2_4b/hopping.def
examples/1D_2_4b/interaction.def
examples/1D_2_4b/interaction.npy
examples/1D_2_4b/model_1D_2_4b.py
examples/1D_2_4b/out
examples/1D_2_4b/s1.pdf
examples/1D_2_4b/s2.pdf
examples/1D_4/GS.tsv
examples/1D_4/ave.tsv
pyqcm.egg-info/PKG-INFO
pyqcm.egg-info/SOURCES.txt
pyqcm.egg-info/dependency_links.txt
pyqcm.egg-info/requires.txt
pyqcm.egg-info/top_level.txt
