Metadata-Version: 2.4
Name: pyqcm
Version: 2.16.0
Summary: Quantum cluster methods for the physics of strongly correlated systems
Home-page: https://bitbucket.org/dsenechQCM/qcm_wed/
Author: David Sénéchal
License: GPL
Requires-Python: >=3.10
License-File: LICENSE.txt
Requires-Dist: matplotlib
Requires-Dist: scipy
Requires-Dist: nlopt>=2.9
Dynamic: author
Dynamic: description
Dynamic: description-content-type
Dynamic: home-page
Dynamic: license
Dynamic: license-file
Dynamic: requires-dist
Dynamic: requires-python
Dynamic: summary
